{"1.0.8": ["Julian Giesen", "jgiesen@uni-koblenz.de"], "1.0.9": ["Julian Giesen", "jgiesen@uni-koblenz.de"], "1.0.17": ["Julian Giesen", "jgiesen@uni-koblenz.de"], "1.0.14": ["Julian Giesen", "jgiesen@uni-koblenz.de"], "1.0.15": ["Julian Giesen", "jgiesen@uni-koblenz.de"], "1.0.13": ["Julian Giesen", "jgiesen@uni-koblenz.de"], "1.0.10": ["Julian Giesen", "jgiesen@uni-koblenz.de"], "1.0.11": ["Julian Giesen", "jgiesen@uni-koblenz.de"], "1.0.27": ["Julian Giesen", "jgiesen@uni-koblenz.de"], "0.1.1": ["Julian Giesen", "jgiesen@uni-koblenz.de"], "1.0.18": ["Julian Giesen", "jgiesen@uni-koblenz.de"]}